composio_livekit/__init__.py
composio_livekit/toolset.py
composio_livekit-0.7.20.dist-info/METADATA
composio_livekit-0.7.20.dist-info/WHEEL
composio_livekit-0.7.20.dist-info/top_level.txt
composio_livekit-0.7.20.dist-info/RECORD
