Metadata-Version: 2.4
Name: composio_livekit
Version: 0.7.20
Summary: Use Composio Toolset with LiveKit
Home-page: https://github.com/ComposioHQ/composio
Author: Sushmitha
Author-email: tech@composio.dev
Classifier: Programming Language :: Python :: 3
Classifier: License :: OSI Approved :: Apache Software License
Classifier: Operating System :: OS Independent
Requires-Python: >=3.9,<4
Requires-Dist: composio_core<0.8.0,>=0.7.0
Requires-Dist: livekit>=0.14.0
Requires-Dist: pydantic>=2.0.0
Requires-Dist: typing-extensions>=4.0.0
Dynamic: author
Dynamic: author-email
Dynamic: classifier
Dynamic: description
Dynamic: description-content-type
Dynamic: home-page
Dynamic: requires-dist
Dynamic: requires-python
Dynamic: summary
